agent_sdk/__init__.py
agent_sdk/core/agent.py
agent_sdk/core/driver.py
agent_sdk/core/types.py
agent_sdk/drivers/cli_json_driver.py
agent_sdk/drivers/copilot_driver.py
agent_sdk/drivers/gemini_driver.py
agent_sdk/drivers/mock_driver.py
agent_sdk/utils/jsonrpc.py
agent_sdk/utils/schema.py
agent_cli_sdk-0.0.1a1.dist-info/METADATA
agent_cli_sdk-0.0.1a1.dist-info/WHEEL
agent_cli_sdk-0.0.1a1.dist-info/licenses/LICENSE
agent_cli_sdk-0.0.1a1.dist-info/RECORD
