Metadata-Version: 2.4
Name: agent-cli-sdk
Version: 0.0.1a1
Summary: Universal SDK for interacting with AI Agent CLIs (Gemini, Copilot, etc.)
Project-URL: Homepage, https://github.com/rbbtsn0w/agent-cli-sdk
Project-URL: Repository, https://github.com/rbbtsn0w/agent-cli-sdk
Project-URL: Issues, https://github.com/rbbtsn0w/agent-cli-sdk/issues
Author-email: Agent CLI SDK Contributors <noreply@github.com>
License: MIT License
License-File: LICENSE
Classifier: Development Status :: 3 - Alpha
Classifier: Intended Audience :: Developers
Classifier: License :: OSI Approved :: MIT License
Classifier: Programming Language :: Python :: 3
Classifier: Programming Language :: Python :: 3.8
Classifier: Programming Language :: Python :: 3.9
Classifier: Programming Language :: Python :: 3.10
Classifier: Programming Language :: Python :: 3.11
Classifier: Topic :: Software Development :: Libraries :: Python Modules
Requires-Python: >=3.8
Requires-Dist: pydantic>=2.0
Provides-Extra: dev
Requires-Dist: pre-commit; extra == 'dev'
Requires-Dist: ruff; extra == 'dev'
Requires-Dist: vulture; extra == 'dev'
Provides-Extra: test
Requires-Dist: pytest; extra == 'test'
Requires-Dist: pytest-asyncio; extra == 'test'
Requires-Dist: pytest-cov; extra == 'test'
Requires-Dist: pytest-timeout; extra == 'test'
